agilecoder/__init__.py
agilecoder/cli.py
agilecoder/run.py
agilecoder/run_api.py
agilecoder/test.py
agilecoder/CompanyConfig/Agile/ChatChainConfig.json
agilecoder/CompanyConfig/Agile/PhaseConfig.json
agilecoder/CompanyConfig/Agile/RoleConfig.json
agilecoder/CompanyConfig/Art/ChatChainConfig.json
agilecoder/CompanyConfig/Default/ChatChainConfig.json
agilecoder/CompanyConfig/Default/PhaseConfig.json
agilecoder/CompanyConfig/Default/RoleConfig.json
agilecoder/camel/__init__.py
agilecoder/camel/configs.py
agilecoder/camel/dependency.py
agilecoder/camel/generators.py
agilecoder/camel/human.py
agilecoder/camel/model_backend.py
agilecoder/camel/typing.py
agilecoder/camel/utils.py
agilecoder/camel/agents/__init__.py
agilecoder/camel/agents/base.py
agilecoder/camel/agents/chat_agent.py
agilecoder/camel/agents/critic_agent.py
agilecoder/camel/agents/embodied_agent.py
agilecoder/camel/agents/role_playing.py
agilecoder/camel/agents/task_agent.py
agilecoder/camel/agents/tool_agents/__init__.py
agilecoder/camel/agents/tool_agents/base.py
agilecoder/camel/agents/tool_agents/hugging_face_tool_agent.py
agilecoder/camel/messages/__init__.py
agilecoder/camel/messages/base.py
agilecoder/camel/messages/chat_messages.py
agilecoder/camel/messages/system_messages.py
agilecoder/camel/prompts/__init__.py
agilecoder/camel/prompts/base.py
agilecoder/camel/prompts/prompt_templates.py
agilecoder/camel/prompts/task_prompt_template.py
agilecoder/components/__init__.py
agilecoder/components/chat_chain.py
agilecoder/components/chat_env.py
agilecoder/components/codes.py
agilecoder/components/composed_phase.py
agilecoder/components/documents.py
agilecoder/components/phase.py
agilecoder/components/roster.py
agilecoder/components/statistics.py
agilecoder/components/utils.py
agilecoder/online_log/__init__.py
agilecoder/online_log/app.py
agilecoder-0.1.9.dist-info/METADATA
agilecoder-0.1.9.dist-info/WHEEL
agilecoder-0.1.9.dist-info/entry_points.txt
agilecoder-0.1.9.dist-info/top_level.txt
agilecoder-0.1.9.dist-info/RECORD
