Metadata-Version: 2.1
Name: agilecoder
Version: 0.1.9
Summary: AgileCoder
Home-page: https://github.com/FSoft-AI4Code/AgileCoder
Author: FSoft-AI4Code
Author-email: support.aic@fpt.com
License: Apache-2.0
Requires-Python: >=3.8
Requires-Dist: openai ==0.28.1
Requires-Dist: tiktoken ==0.6.0
Requires-Dist: markdown ==3.5.2
Requires-Dist: colorama
Requires-Dist: nltk ==3.8.1
Requires-Dist: flask
Requires-Dist: tenacity ==8.2.3
Requires-Dist: python-dotenv
Requires-Dist: codebleu ==0.7.0
Requires-Dist: google-auth
Requires-Dist: google-auth-oauthlib
Requires-Dist: google-auth-httplib2
Requires-Dist: anthropic
Requires-Dist: pygame
Requires-Dist: numpy
Requires-Dist: tree-sitter
